{
    "resource": "/lists/{id}",
    "path": "/lists/cf19fb62",
    "httpMethod": "PUT",
    "body": "{\n    \"attribute_name\": \"title\",\n    \"attribute_value\": \"My new title\"\n}",
    "headers": {
        "Accept": "*/*",
        "Accept-Encoding": "gzip, deflate",
        "Cache-Control": "no-cache",
        "CloudFront-Forwarded-Proto": "https",
        "CloudFront-Is-Desktop-Viewer": "true",
        "CloudFront-Is-Mobile-Viewer": "false",
        "CloudFront-Is-SmartTV-Viewer": "false",
        "CloudFront-Is-Tablet-Viewer": "false",
        "CloudFront-Viewer-Country": "GB",
        "Content-Type": "text/plain",
        "Host": "4sdcvv0n2e.execute-api.eu-west-1.amazonaws.com",
        "Postman-Token": "d38bfa3c-26b3-4a42-acfa-ecc30a12d767",
        "User-Agent": "PostmanRuntime/7.15.2",
        "Via": "1.1 f76142b838785e2eec49408a3d9d8285.cloudfront.net (CloudFront)",
        "X-Amz-Cf-Id": "pUhW1u14GSPTlHCQed4C5eTsM3Biv_ca3cDVCh9hbcnZ3_e4z0CgVw==",
        "x-amz-content-sha256": "51f3f8790f9b06462165164ab5e1bf33fd64f8230e962c445681a63555e04429",
        "x-amz-date": "20191007T160043Z",
        "X-Amzn-Trace-Id": "Root=1-5d9b612b-c2a6fbd0452771f0b0155f70",
        "X-Forwarded-For": "5.81.150.55, 70.132.15.71",
        "X-Forwarded-Port": "443",
        "X-Forwarded-Proto": "https"
    },
    "queryStringParameters": null,
    "multiValueQueryStringParameters": null,
    "pathParameters": {
        "id": "cf19fb62"
    },
    "stageVariables": null,
    "requestContext": {
        "resourceId": "4j13uq",
        "resourcePath": "/lists/{id}",
        "httpMethod": "PUT",
        "extendedRequestId": "BMwexGf4DoEFoJA=",
        "requestTime": "07/Oct/2019:16:00:43 +0000",
        "path": "/test/lists/cf19fb62",
        "accountId": "123456789012",
        "protocol": "HTTP/1.1",
        "stage": "test",
        "domainPrefix": "4sdcvv0n2e",
        "requestTimeEpoch": 1570464043231,
        "requestId": "c410dfa4-713a-4ac3-afe5-2e3ab3d4066f",
        "identity": {
            "cognitoIdentityPoolId": null,
            "accountId": "123456789012",
            "cognitoIdentityId": null,
            "caller": "ABCDEFGPDMJL4EB35H6H",
            "sourceIp": "5.81.150.55",
            "principalOrgId": "o-d8jj6dyqv2",
            "accessKey": "ABCDEFGPDMJL4EB35H6H",
            "cognitoAuthenticationType": null,
            "cognitoAuthenticationProvider": null,
            "userArn": "arn:aws:iam::123456789012:user/ApiTestUser",
            "userAgent": "PostmanRuntime/7.15.2",
            "user": "ABCDEFGPDMJL4EB35H6H"
        },
        "domainName": "4sdcvv0n2e.execute-api.eu-west-1.amazonaws.com",
        "apiId": "4sdcvv0n2e"
    },
    "isBase64Encoded": false
}
